hpc05_culler.py
hpc05_monitor.py
hpc05/__init__.py
hpc05/_static_version.py
hpc05/_version.py
hpc05/client.py
hpc05/connect.py
hpc05/profile.py
hpc05/ssh_utils.py
hpc05/utils.py
hpc05-2.0.6.dist-info/LICENSE
hpc05-2.0.6.dist-info/METADATA
hpc05-2.0.6.dist-info/WHEEL
hpc05-2.0.6.dist-info/top_level.txt
hpc05-2.0.6.dist-info/RECORD
