Metadata-Version: 2.1
Name: hpc05
Version: 2.0.6
Summary: Client package for PBS and SLURM clusters with a headnode.
Home-page: https://github.com/basnijholt/hpc05
Author: Bas Nijholt
Author-email: basnijholt@gmail.com
License: MIT
Platform: UNKNOWN
Classifier: License :: OSI Approved :: MIT License
Classifier: Operating System :: OS Independent
Classifier: Programming Language :: Python :: 3.7
Classifier: Programming Language :: Python :: 3.7
Requires-Python: >=3.6
Requires-Dist: ipyparallel
Requires-Dist: pexpect
Requires-Dist: pyzmq
Requires-Dist: paramiko
Requires-Dist: tornado
Requires-Dist: psutil
Provides-Extra: dev
Requires-Dist: pre-commit ; extra == 'dev'
Provides-Extra: docs
Requires-Dist: sphinx ; extra == 'docs'
Requires-Dist: sphinx-rtd-theme ; extra == 'docs'
Requires-Dist: m2r ; extra == 'docs'
Requires-Dist: sphinxcontrib.apidoc ; extra == 'docs'
